CHANGES.txt
LICENSE.txt
README.rst
bootstrap.py
setup.py
js/__init__.py
js.jqgrid.egg-info/PKG-INFO
js.jqgrid.egg-info/SOURCES.txt
js.jqgrid.egg-info/dependency_links.txt
js.jqgrid.egg-info/entry_points.txt
js.jqgrid.egg-info/namespace_packages.txt
js.jqgrid.egg-info/not-zip-safe
js.jqgrid.egg-info/requires.txt
js.jqgrid.egg-info/top_level.txt
js/jqgrid/__init__.py
js/jqgrid/resources/README.txt
js/jqgrid/resources/css/ellipsis-xbl.xml
js/jqgrid/resources/css/ui.jqgrid.css
js/jqgrid/resources/js/Changes.txt
js/jqgrid/resources/js/install.txt
js/jqgrid/resources/js/jquery.jqGrid.min.js
js/jqgrid/resources/js/jquery.jqGrid.src.js
js/jqgrid/resources/js/i18n/grid.locale-ar.js
js/jqgrid/resources/js/i18n/grid.locale-bg.js
js/jqgrid/resources/js/i18n/grid.locale-bg1251.js
js/jqgrid/resources/js/i18n/grid.locale-cat.js
js/jqgrid/resources/js/i18n/grid.locale-cn.js
js/jqgrid/resources/js/i18n/grid.locale-cs.js
js/jqgrid/resources/js/i18n/grid.locale-da.js
js/jqgrid/resources/js/i18n/grid.locale-de.js
js/jqgrid/resources/js/i18n/grid.locale-dk.js
js/jqgrid/resources/js/i18n/grid.locale-el.js
js/jqgrid/resources/js/i18n/grid.locale-en.js
js/jqgrid/resources/js/i18n/grid.locale-es.js
js/jqgrid/resources/js/i18n/grid.locale-fa.js
js/jqgrid/resources/js/i18n/grid.locale-fi.js
js/jqgrid/resources/js/i18n/grid.locale-fr.js
js/jqgrid/resources/js/i18n/grid.locale-gl.js
js/jqgrid/resources/js/i18n/grid.locale-he.js
js/jqgrid/resources/js/i18n/grid.locale-hr.js
js/jqgrid/resources/js/i18n/grid.locale-hr1250.js
js/jqgrid/resources/js/i18n/grid.locale-hu.js
js/jqgrid/resources/js/i18n/grid.locale-is.js
js/jqgrid/resources/js/i18n/grid.locale-it.js
js/jqgrid/resources/js/i18n/grid.locale-ja.js
js/jqgrid/resources/js/i18n/grid.locale-kr.js
js/jqgrid/resources/js/i18n/grid.locale-lt.js
js/jqgrid/resources/js/i18n/grid.locale-mne.js
js/jqgrid/resources/js/i18n/grid.locale-nl.js
js/jqgrid/resources/js/i18n/grid.locale-no.js
js/jqgrid/resources/js/i18n/grid.locale-pl.js
js/jqgrid/resources/js/i18n/grid.locale-pt-br.js
js/jqgrid/resources/js/i18n/grid.locale-pt.js
js/jqgrid/resources/js/i18n/grid.locale-ro.js
js/jqgrid/resources/js/i18n/grid.locale-ru.js
js/jqgrid/resources/js/i18n/grid.locale-sk.js
js/jqgrid/resources/js/i18n/grid.locale-sr-latin.js
