Metadata-Version: 1.0
Name: js.jqgrid
Version: 4.4.1-1
Summary: Fanstatic packaging of jqgrid
Home-page: https://github.com/do3cc/js.jqgrid
Author: Fanstatic Developers
Author-email: fanstatic@googlegroups.com
License: UNKNOWN
Keywords: jqgrid
Platform: UNKNOWN
